kiri_walkgame/__init__.py
kiri_walkgame/characters.py
kiri_walkgame/output.py
kiri_walkgame/shortcuts.py
kiri_walkgame/sources/audios/Fantasy_by_Pufino_on_freetouse_com.mp3
kiri_walkgame/sources/audios/meow.mp3
kiri_walkgame/sources/box.png
kiri_walkgame/sources/icons/refresh.png
kiri_walkgame/sources/icons/voice_off.png
kiri_walkgame/sources/icons/voice_on.png
kiri_walkgame/sources/kiri/run.png
kiri_walkgame/sources/kiri/stand.png
kiri_walkgame/sources/logo.png
kiri_walkgame-1.2.0.dist-info/LICENSE
kiri_walkgame-1.2.0.dist-info/METADATA
kiri_walkgame-1.2.0.dist-info/WHEEL
kiri_walkgame-1.2.0.dist-info/entry_points.txt
kiri_walkgame-1.2.0.dist-info/RECORD
