Metadata-Version: 2.1
Name: kiri-walkgame
Version: 1.2.0
Summary: a mini game to visualize the path-finding algorithm
Home-page: https://github.com/kiri-chow/kiri-walkgame
License: MIT
Author: anthony
Author-email: mrchowpoor@gmail.com
Requires-Python: >=3.9,<4.0
Classifier: License :: OSI Approved :: MIT License
Classifier: Programming Language :: Python :: 3
Classifier: Programming Language :: Python :: 3.9
Classifier: Programming Language :: Python :: 3.10
Classifier: Programming Language :: Python :: 3.11
Requires-Dist: kiri-pathfinding (>=1.2.0,<2.0.0)
Requires-Dist: pygame (>=2.5.0,<3.0.0)
Requires-Dist: pypng (>=0.20220715.0,<0.20220716.0)
Project-URL: Repository, https://github.com/kiri-chow/kiri-walkgame
